moteus/__init__.py
moteus/aioserial.py
moteus/aiostream.py
moteus/calibrate_encoder.py
moteus/command.py
moteus/device_info.py
moteus/export.py
moteus/fdcanusb.py
moteus/fdcanusb_device.py
moteus/moteus.py
moteus/moteus_tool.py
moteus/multiplex.py
moteus/posix_aioserial.py
moteus/protocol.py
moteus/pythoncan.py
moteus/pythoncan_device.py
moteus/reader.py
moteus/regression.py
moteus/transport.py
moteus/transport_device.py
moteus/transport_factory.py
moteus/transport_wrapper.py
moteus/version.py
moteus/win32_aioserial.py
moteus-0.3.98.dist-info/METADATA
moteus-0.3.98.dist-info/WHEEL
moteus-0.3.98.dist-info/entry_points.txt
moteus-0.3.98.dist-info/top_level.txt
moteus-0.3.98.dist-info/RECORD
