Metadata-Version: 2.1
Name: moteus
Version: 0.3.98
Summary: moteus brushless controller library and tools
Home-page: https://github.com/mjbots/moteus
Author: mjbots Robotic Systems
Author-email: info@mjbots.com
Keywords: moteus
Classifier: Development Status :: 3 - Alpha
Classifier: Intended Audience :: Developers
Classifier: License :: OSI Approved :: Apache Software License
Classifier: Programming Language :: Python :: 3
Requires-Python: >=3.7, <4
Requires-Dist: importlib-metadata >=3.6
Requires-Dist: packaging
Requires-Dist: pyelftools >=0.26
Requires-Dist: pyserial >=3.5
Requires-Dist: python-can >=3.3
Requires-Dist: scipy >=1.8.0
Requires-Dist: pywin32 ; platform_system == "Windows"
